Metadata-Version: 1.1
Name: stpipeline
Version: 1.8.1
Summary: ST Pipeline: An automated pipeline for spatial mapping of unique transcripts
Home-page: https://github.com/SpatialTranscriptomicsResearch/st_pipeline
Author: Jose Fernandez Navarro
Author-email: jc.fernandez.navarro@gmail.com
License: MIT
Keywords: rna-seq analysis spatial transcriptomics toolkit
Platform: UNKNOWN
Classifier: Development Status :: 5 - Production/Stable
Classifier: Intended Audience :: Science/Research
Classifier: Topic :: Software Development
Classifier: Topic :: Scientific/Engineering :: Bio-Informatics
Classifier: License :: OSI Approved :: MIT License
Classifier: Programming Language :: Python :: 3.6
Classifier: Programming Language :: Python :: 3.7
Classifier: Operating System :: Unix
Classifier: Operating System :: MacOS
Classifier: Environment :: Console
